pyvelop/__init__.py
pyvelop/__main__.py
pyvelop/const.py
pyvelop/decorators.py
pyvelop/exceptions.py
pyvelop/jnap.py
pyvelop/logger.py
pyvelop/mesh.py
pyvelop/mesh_entity.py
pyvelop/types.py
pyvelop-2025.9.1.dist-info/METADATA
pyvelop-2025.9.1.dist-info/WHEEL
pyvelop-2025.9.1.dist-info/top_level.txt
pyvelop-2025.9.1.dist-info/RECORD
