Metadata-Version: 2.4
Name: pyvelop
Version: 2025.9.1
Summary: A Python library for the Linksys Velop Mesh system
Author: uvjim
Project-URL: Homepage, https://github.com/uvjim/pyvelop
Project-URL: Repository, https://github.com/uvjim/pyvelop
Project-URL: Issues, https://github.com/uvjim/pyvelop/issues
Requires-Python: >=3.12
Requires-Dist: aiohttp
Provides-Extra: cli
Requires-Dist: asyncclick; extra == "cli"
